detect_delimiter.py
detect_delimiter-0.1.1.dist-info/METADATA
detect_delimiter-0.1.1.dist-info/RECORD
detect_delimiter-0.1.1.dist-info/WHEEL
detect_delimiter-0.1.1.dist-info/top_level.txt
