Metadata-Version: 2.1
Name: detect_delimiter
Version: 0.1.1
Summary: Detects the delimiter used in CSV, TSV and other ad hoc file formats.
Home-page: https://git.nzoss.org.nz/tim-mcnamara/detect-delimiter
Author: Tim McNamara
Author-email: paperless@timmcnamara.co.nz
License: UNKNOWN
Platform: UNKNOWN
Classifier: Development Status :: 4 - Beta
Classifier: License :: OSI Approved :: Apache Software License
Classifier: Intended Audience :: Developers
Classifier: Natural Language :: English
Classifier: Programming Language :: Python :: 3
Classifier: Topic :: Software Development :: Libraries
Classifier: Topic :: Text Processing
Classifier: Topic :: Utilities
